MANIFEST.in
README.rst
setup.py
van/__init__.py
van.resumelb.egg-info/PKG-INFO
van.resumelb.egg-info/SOURCES.txt
van.resumelb.egg-info/dependency_links.txt
van.resumelb.egg-info/namespace_packages.txt
van.resumelb.egg-info/requires.txt
van.resumelb.egg-info/top_level.txt
van/resumelb/__init__.py
van/resumelb/pool.test
van/resumelb/tests.py