Metadata-Version: 1.0
Name: van.resumelb
Version: 0.5
Summary: Pool class for zc.resumelb which divides workers by version
Home-page: http://pypi.python.org/pypi/van.resumelb
Author: Vanguardistas LLC
Author-email: brian@vanguardistas.net
License: BSD-derived
Platform: UNKNOWN
